examples/example_usage.py
terag/__init__.py
terag/core.py
terag/embeddings/__init__.py
terag/embeddings/cache.py
terag/embeddings/manager.py
terag/graph/__init__.py
terag/graph/builder.py
terag/graph/deduplication.py
terag/graph/merger.py
terag/graph/types.py
terag/ingestion/__init__.py
terag/ingestion/groq_client.py
terag/ingestion/json_ingestion.py
terag/ingestion/llm_providers.py
terag/ingestion/ner_extraction.py
terag/ingestion/ner_extractor.py
terag/ingestion/pipeline.py
terag/ingestion/query_ner.py
terag/retrieval/__init__.py
terag/retrieval/hybrid.py
terag/retrieval/ppr.py
terag/retrieval/query_processor.py
terag/retrieval/semantic.py
terag/utils/__init__.py
terag/utils/edge_weights.py
terag-0.8.0.dist-info/licenses/LICENSE
terag-0.8.0.dist-info/METADATA
terag-0.8.0.dist-info/WHEEL
terag-0.8.0.dist-info/top_level.txt
terag-0.8.0.dist-info/RECORD
