Metadata-Version: 2.4
Name: terag
Version: 0.8.0
Summary: Token-Efficient Retrieval Augmented Generation with Graph-based Indexing
Author-email: Rudra Naik <rudra91@gmail.com>
License: MIT License
Project-URL: Homepage, https://github.com/rudranaik/terag
Project-URL: Bug Tracker, https://github.com/rudranaik/terag/issues
Classifier: Programming Language :: Python :: 3
Classifier: License :: OSI Approved :: MIT License
Classifier: Operating System :: OS Independent
Requires-Python: >=3.8
License-File: LICENSE
Requires-Dist: numpy
Requires-Dist: networkx
Requires-Dist: scikit-learn
Requires-Dist: openai
Requires-Dist: tiktoken
Requires-Dist: groq
Requires-Dist: python-dotenv
Requires-Dist: tqdm
Provides-Extra: dev
Requires-Dist: pytest; extra == "dev"
Requires-Dist: black; extra == "dev"
Requires-Dist: isort; extra == "dev"
Provides-Extra: fuzzy
Requires-Dist: fuzzywuzzy; extra == "fuzzy"
Requires-Dist: python-Levenshtein; extra == "fuzzy"
Dynamic: license-file
